{
    "latencies": [
        {
            "frame": 0,
            "rtt": []
        },
        {
            "frame": 1,
            "rtt": [
                31.711999893188478,
                27.19622039794922,
                32.93830490112305,
                25.450481414794923,
                33.49122619628906
            ]
        },
        {
            "frame": 2,
            "rtt": [
                23.746917724609376,
                28.505884170532228,
                32.873268127441409,
                28.13153076171875,
                35.48374938964844
            ]
        },
        {
            "frame": 3,
            "rtt": [
                28.01955795288086,
                25.396129608154298,
                28.575620651245118,
                25.986148834228517,
                32.569786071777347
            ]
        },
        {
            "frame": 4,
            "rtt": [
                23.752302169799806,
                26.211742401123048,
                28.64016342163086,
                26.89850616455078,
                33.449310302734378
            ]
        },
        {
            "frame": 5,
            "rtt": [
                23.764286041259767,
                26.228599548339845,
                27.61017608642578,
                33.51374816894531,
                33.474361419677737
            ]
        },
        {
            "frame": 6,
            "rtt": [
                17.819149017333986,
                25.155759811401368,
                27.822389602661134,
                26.917041778564454,
                25.276742935180665
            ]
        },
        {
            "frame": 7,
            "rtt": [
                19.49705696105957,
                28.32610511779785,
                30.834152221679689,
                27.669963836669923,
                26.27731704711914
            ]
        },
        {
            "frame": 8,
            "rtt": [
                17.953777313232423,
                25.28731918334961,
                28.010391235351564,
                26.950607299804689,
                25.22549057006836
            ]
        },
        {
            "frame": 9,
            "rtt": [
                19.617258071899415,
                27.811676025390626,
                27.764381408691408,
                26.345754623413087
            ]
        },
        {
            "frame": 10,
            "rtt": [
                19.89409637451172,
                27.725069046020509,
                27.824493408203126,
                26.38728904724121
            ]
        },
        {
            "frame": 11,
            "rtt": [
                19.776893615722658,
                28.9547119140625,
                28.340600967407228,
                25.191503524780275
            ]
        },
        {
            "frame": 12,
            "rtt": [
                20.0706844329834,
                25.566192626953126
            ]
        },
        {
            "frame": 13,
            "rtt": [
                24.69316864013672,
                25.881717681884767
            ]
        },
        {
            "frame": 14,
            "rtt": [
                24.717296600341798,
                26.01847267150879
            ]
        },
        {
            "frame": 15,
            "rtt": [
                24.752269744873048,
                20.358686447143556
            ]
        },
        {
            "frame": 16,
            "rtt": [
                24.79806900024414,
                26.30881118774414
            ]
        },
        {
            "frame": 17,
            "rtt": [
                24.85470962524414,
                34.99289321899414
            ]
        },
        {
            "frame": 18,
            "rtt": [
                14.464001655578614,
                20.438304901123048,
                20.22368049621582,
                25.254480361938478
            ]
        },
        {
            "frame": 19,
            "rtt": [
                17.538654327392579,
                33.27033233642578,
                25.00059700012207,
                26.505535125732423
            ]
        },
        {
            "frame": 20,
            "rtt": [
                16.216215133666993,
                15.683296203613282,
                20.31784439086914,
                20.52810287475586,
                24.702476501464845
            ]
        },
        {
            "frame": 21,
            "rtt": [
                27.573246002197267,
                17.877580642700197,
                25.189611434936525,
                32.87753677368164,
                26.897417068481447
            ]
        },
        {
            "frame": 22,
            "rtt": [
                16.840784072875978,
                16.060731887817384,
                20.433528900146486,
                20.646427154541017,
                24.72122573852539
            ]
        },
        {
            "frame": 23,
            "rtt": [
                16.911048889160158,
                18.24933624267578,
                25.42108154296875,
                32.51068115234375,
                27.319259643554689
            ]
        },
        {
            "frame": 24,
            "rtt": [
                16.24286460876465,
                15.848433494567871,
                21.613073348999025,
                20.79250717163086,
                24.768451690673829
            ]
        },
        {
            "frame": 25,
            "rtt": [
                17.074548721313478,
                23.098583221435548,
                24.606260299682618,
                22.859771728515626,
                24.803604125976564
            ]
        },
        {
            "frame": 26,
            "rtt": [
                26.739418029785158,
                32.01206588745117,
                26.757932662963868,
                29.43918800354004,
                32.52191925048828
            ]
        },
        {
            "frame": 27,
            "rtt": [
                16.350292205810548,
                21.062110900878908,
                22.382762908935548,
                33.35197830200195,
                32.702659606933597
            ]
        },
        {
            "frame": 28,
            "rtt": [
                21.16504669189453,
                22.4107608795166,
                28.511396408081056,
                25.45193099975586,
                33.49188232421875
            ]
        },
        {
            "frame": 29,
            "rtt": [
                23.746864318847658,
                28.504913330078126,
                31.769289016723634,
                27.135536193847658,
                32.62351989746094
            ]
        },
        {
            "frame": 30,
            "rtt": [
                23.34136962890625,
                25.354389190673829,
                28.63436508178711,
                27.17286491394043,
                32.598331451416019
            ]
        },
        {
            "frame": 31,
            "rtt": [
                23.762962341308595,
                28.589643478393556,
                28.673370361328126,
                36.43111038208008,
                33.457862854003909
            ]
        },
        {
            "frame": 32,
            "rtt": [
                18.586030960083009,
                27.80770492553711,
                30.710729598999025,
                26.915924072265626,
                25.27947425842285
            ]
        },
        {
            "frame": 33,
            "rtt": [
                18.660688400268556,
                28.015811920166017,
                28.047983169555665,
                27.66664695739746,
                26.274782180786134
            ]
        },
        {
            "frame": 34,
            "rtt": [
                17.952533721923829,
                25.288360595703126,
                28.0102481842041,
                26.94883918762207,
                31.426542282104493
            ]
        },
        {
            "frame": 35,
            "rtt": [
                17.968441009521486,
                25.129634857177736,
                25.209667205810548,
                29.968461990356447
            ]
        },
        {
            "frame": 36,
            "rtt": [
                19.681917190551759,
                27.732288360595704,
                27.81896209716797,
                26.383481979370118
            ]
        },
        {
            "frame": 37,
            "rtt": [
                19.786823272705079,
                28.93977928161621,
                27.026653289794923,
                25.1917667388916
            ]
        },
        {
            "frame": 38,
            "rtt": [
                19.12444496154785,
                24.367015838623048
            ]
        },
        {
            "frame": 39,
            "rtt": [
                25.98748207092285,
                34.60655212402344
            ]
        },
        {
            "frame": 40,
            "rtt": [
                24.714786529541017,
                26.006452560424806
            ]
        },
        {
            "frame": 41,
            "rtt": [
                20.119768142700197,
                20.357385635375978
            ]
        },
        {
            "frame": 42,
            "rtt": [
                20.147987365722658,
                20.37581443786621
            ]
        },
        {
            "frame": 43,
            "rtt": [
                24.849380493164064,
                35.006649017333987
            ]
        },
        {
            "frame": 44,
            "rtt": [
                14.464325904846192,
                20.435075759887697,
                23.909191131591798,
                25.262907028198243
            ]
        },
        {
            "frame": 45,
            "rtt": [
                15.658360481262207,
                20.475732803344728,
                20.26405143737793,
                24.704137802124025
            ]
        },
        {
            "frame": 46,
            "rtt": [
                27.772289276123048,
                17.689220428466798,
                25.081586837768556,
                33.08782958984375,
                26.680591583251954
            ]
        },
        {
            "frame": 47,
            "rtt": [
                16.773279190063478,
                16.131839752197267,
                23.518688201904298,
                24.48436737060547,
                25.00861358642578
            ]
        },
        {
            "frame": 48,
            "rtt": [
                16.212194442749025,
                15.748153686523438,
                23.40415382385254,
                24.50322723388672,
                24.94267463684082
            ]
        },
        {
            "frame": 49,
            "rtt": [
                27.237592697143556,
                15.792448997497559,
                20.49367904663086,
                20.70976448059082,
                24.739253997802736
            ]
        },
        {
            "frame": 50,
            "rtt": [
                16.982044219970704,
                15.843695640563965,
                20.5648250579834,
                20.78565216064453,
                24.76583480834961
            ]
        }
    ]
}