{
    "latencies": [
        {
            "frame": 0,
            "rtt": []
        },
        {
            "frame": 1,
            "rtt": [
                93.56668853759766,
                106.41761016845703,
                121.21675872802735
            ]
        },
        {
            "frame": 2,
            "rtt": [
                93.55245971679688,
                106.40191650390625,
                121.2143325805664
            ]
        },
        {
            "frame": 3,
            "rtt": [
                112.89250946044922,
                106.40107727050781,
                121.21439361572266
            ]
        },
        {
            "frame": 4,
            "rtt": []
        },
        {
            "frame": 5,
            "rtt": []
        },
        {
            "frame": 6,
            "rtt": []
        },
        {
            "frame": 7,
            "rtt": []
        },
        {
            "frame": 8,
            "rtt": []
        },
        {
            "frame": 9,
            "rtt": [
                145.51226806640626,
                142.74774169921876
            ]
        },
        {
            "frame": 10,
            "rtt": [
                118.61480712890625,
                130.62168884277345
            ]
        },
        {
            "frame": 11,
            "rtt": [
                112.74595642089844,
                130.5565185546875
            ]
        },
        {
            "frame": 12,
            "rtt": [
                147.0039520263672,
                171.346923828125,
                124.23051452636719
            ]
        },
        {
            "frame": 13,
            "rtt": [
                92.25411987304688,
                107.9665756225586,
                121.94988250732422
            ]
        },
        {
            "frame": 14,
            "rtt": [
                142.8907012939453,
                114.53950500488281,
                128.3600616455078
            ]
        },
        {
            "frame": 15,
            "rtt": [
                92.23616790771485,
                107.9072265625,
                121.7785873413086
            ]
        },
        {
            "frame": 16,
            "rtt": [
                141.89674377441407,
                114.33009338378906,
                128.25987243652345
            ]
        },
        {
            "frame": 17,
            "rtt": [
                141.89675903320313,
                108.27896118164063,
                124.18370819091797
            ]
        },
        {
            "frame": 18,
            "rtt": [
                117.50940704345703,
                124.6732406616211,
                149.62696838378907
            ]
        },
        {
            "frame": 19,
            "rtt": [
                92.2686538696289,
                107.85993194580078,
                149.4521026611328
            ]
        },
        {
            "frame": 20,
            "rtt": [
                117.4283218383789,
                107.86328125,
                121.44876861572266
            ]
        },
        {
            "frame": 21,
            "rtt": [
                92.3185806274414,
                107.87291717529297,
                121.3996810913086
            ]
        },
        {
            "frame": 22,
            "rtt": [
                121.90725708007813,
                125.71542358398438,
                137.49049377441407
            ]
        },
        {
            "frame": 23,
            "rtt": [
                121.92214965820313,
                125.5843505859375,
                133.03253173828126
            ]
        },
        {
            "frame": 24,
            "rtt": [
                125.46033477783203,
                121.28656768798828
            ]
        },
        {
            "frame": 25,
            "rtt": [
                111.9851303100586,
                126.54930877685547
            ]
        },
        {
            "frame": 26,
            "rtt": [
                94.50861358642578,
                108.16334533691406,
                124.65980529785156
            ]
        },
        {
            "frame": 27,
            "rtt": [
                93.58430480957031,
                106.436767578125,
                121.22545623779297
            ]
        },
        {
            "frame": 28,
            "rtt": [
                112.5606918334961,
                111.73343658447266,
                137.80946350097657
            ]
        },
        {
            "frame": 29,
            "rtt": [
                134.83596801757813,
                108.22862243652344,
                124.95524597167969
            ]
        },
        {
            "frame": 30,
            "rtt": []
        }
    ]
}