{
    "latencies": [
        {
            "frame": 0,
            "rtt": []
        },
        {
            "frame": 1,
            "rtt": [
                25.856599807739259,
                45.52488327026367
            ]
        },
        {
            "frame": 2,
            "rtt": [
                19.23089599609375,
                33.52425765991211
            ]
        },
        {
            "frame": 3,
            "rtt": [
                20.00087547302246,
                33.755821228027347
            ]
        },
        {
            "frame": 4,
            "rtt": [
                23.897689819335939,
                34.829952239990237
            ]
        },
        {
            "frame": 5,
            "rtt": [
                25.119029998779298,
                33.94409942626953,
                33.447322845458987
            ]
        },
        {
            "frame": 6,
            "rtt": [
                30.87409210205078,
                30.910892486572267
            ]
        },
        {
            "frame": 7,
            "rtt": [
                35.33026885986328
            ]
        },
        {
            "frame": 8,
            "rtt": [
                33.37782287597656
            ]
        },
        {
            "frame": 9,
            "rtt": [
                33.17905807495117
            ]
        },
        {
            "frame": 10,
            "rtt": []
        },
        {
            "frame": 11,
            "rtt": []
        },
        {
            "frame": 12,
            "rtt": [
                54.51540756225586,
                35.14262771606445,
                36.62354278564453
            ]
        },
        {
            "frame": 13,
            "rtt": [
                27.306596755981447,
                35.16123962402344,
                34.41224670410156
            ]
        },
        {
            "frame": 14,
            "rtt": [
                38.36744689941406,
                45.06043243408203,
                32.99309158325195
            ]
        },
        {
            "frame": 15,
            "rtt": [
                25.58378028869629,
                33.03312301635742,
                32.97943115234375
            ]
        },
        {
            "frame": 16,
            "rtt": [
                25.980491638183595,
                33.72439193725586,
                34.8645133972168
            ]
        },
        {
            "frame": 17,
            "rtt": [
                25.35613250732422,
                33.258758544921878,
                32.97269821166992
            ]
        },
        {
            "frame": 18,
            "rtt": [
                24.290924072265626,
                32.26020431518555,
                48.3757209777832
            ]
        },
        {
            "frame": 19,
            "rtt": [
                26.993392944335939,
                35.54627990722656,
                32.993194580078128
            ]
        },
        {
            "frame": 20,
            "rtt": []
        },
        {
            "frame": 21,
            "rtt": []
        },
        {
            "frame": 22,
            "rtt": []
        },
        {
            "frame": 23,
            "rtt": []
        },
        {
            "frame": 24,
            "rtt": [
                43.680519104003909
            ]
        },
        {
            "frame": 25,
            "rtt": [
                45.918212890625
            ]
        },
        {
            "frame": 26,
            "rtt": [
                43.29494857788086,
                43.5021858215332
            ]
        },
        {
            "frame": 27,
            "rtt": [
                38.234806060791019,
                41.693519592285159
            ]
        },
        {
            "frame": 28,
            "rtt": [
                25.855224609375,
                33.66245651245117
            ]
        },
        {
            "frame": 29,
            "rtt": [
                19.999948501586915,
                33.76399230957031
            ]
        },
        {
            "frame": 30,
            "rtt": [
                40.04850769042969,
                30.985567092895509
            ]
        },
        {
            "frame": 31,
            "rtt": [
                31.04946517944336,
                30.918968200683595,
                30.85152816772461
            ]
        },
        {
            "frame": 32,
            "rtt": [
                30.871925354003908,
                30.911184310913087
            ]
        },
        {
            "frame": 33,
            "rtt": [
                30.9053897857666,
                31.053510665893556
            ]
        },
        {
            "frame": 34,
            "rtt": [
                30.999977111816408
            ]
        },
        {
            "frame": 35,
            "rtt": [
                35.540592193603519
            ]
        },
        {
            "frame": 36,
            "rtt": []
        },
        {
            "frame": 37,
            "rtt": []
        },
        {
            "frame": 38,
            "rtt": [
                54.51862335205078,
                35.141441345214847,
                36.619014739990237
            ]
        },
        {
            "frame": 39,
            "rtt": [
                24.547283172607423,
                35.15922927856445,
                36.67467498779297
            ]
        },
        {
            "frame": 40,
            "rtt": [
                54.45371627807617,
                56.37168502807617,
                45.50386047363281
            ]
        },
        {
            "frame": 41,
            "rtt": [
                48.36040496826172,
                55.01774215698242,
                32.98031997680664
            ]
        },
        {
            "frame": 42,
            "rtt": [
                54.41015625,
                33.735687255859378,
                34.85085678100586
            ]
        },
        {
            "frame": 43,
            "rtt": [
                26.17965316772461,
                35.322845458984378,
                47.90427780151367
            ]
        },
        {
            "frame": 44,
            "rtt": [
                31.369197845458986,
                39.27095413208008,
                39.57487487792969
            ]
        },
        {
            "frame": 45,
            "rtt": [
                32.780006408691409,
                41.892555236816409,
                38.61186981201172
            ]
        },
        {
            "frame": 46,
            "rtt": []
        },
        {
            "frame": 47,
            "rtt": []
        },
        {
            "frame": 48,
            "rtt": []
        },
        {
            "frame": 49,
            "rtt": []
        },
        {
            "frame": 50,
            "rtt": [
                43.69808578491211
            ]
        }
    ]
}