{
    "latencies": [
        {
            "frame": 0,
            "rtt": []
        },
        {
            "frame": 1,
            "rtt": [
                45.647789001464847,
                54.865943908691409,
                176.7412872314453,
                106.03044128417969
            ]
        },
        {
            "frame": 2,
            "rtt": [
                32.557960510253909,
                44.07914352416992,
                38.87785720825195,
                46.69342041015625,
                59.84275436401367
            ]
        },
        {
            "frame": 3,
            "rtt": [
                59.383811950683597,
                36.02240753173828,
                39.24047088623047,
                53.4945068359375,
                69.00772094726563
            ]
        },
        {
            "frame": 4,
            "rtt": [
                80.75653076171875,
                53.45245361328125,
                69.03426361083985
            ]
        },
        {
            "frame": 5,
            "rtt": [
                80.77051544189453,
                89.95042419433594,
                69.06260681152344
            ]
        },
        {
            "frame": 6,
            "rtt": [
                35.07569122314453,
                77.0384521484375,
                69.97746276855469,
                82.59965515136719
            ]
        },
        {
            "frame": 7,
            "rtt": [
                42.863853454589847,
                47.50790786743164,
                62.07730484008789,
                55.491764068603519,
                73.26213073730469
            ]
        },
        {
            "frame": 8,
            "rtt": [
                57.366371154785159,
                67.42532348632813,
                44.00810241699219,
                46.987892150878909,
                57.61787796020508
            ]
        },
        {
            "frame": 9,
            "rtt": [
                59.12303924560547,
                53.36984634399414,
                64.06745147705078
            ]
        },
        {
            "frame": 10,
            "rtt": [
                43.302520751953128,
                99.51727294921875,
                53.367164611816409,
                63.9159049987793
            ]
        },
        {
            "frame": 11,
            "rtt": [
                34.80923080444336,
                38.90930938720703,
                56.184051513671878,
                53.36983108520508,
                63.90552520751953
            ]
        },
        {
            "frame": 12,
            "rtt": [
                47.21826171875,
                60.3243522644043,
                44.63743591308594,
                63.90652847290039
            ]
        },
        {
            "frame": 13,
            "rtt": [
                53.39157485961914,
                59.538482666015628,
                75.45449829101563
            ]
        },
        {
            "frame": 14,
            "rtt": [
                78.23560333251953,
                84.76560974121094,
                57.858665466308597
            ]
        },
        {
            "frame": 15,
            "rtt": [
                34.760772705078128,
                54.07853317260742,
                107.5951156616211,
                92.83808135986328,
                93.04805755615235
            ]
        },
        {
            "frame": 16,
            "rtt": [
                44.33605194091797,
                47.483001708984378,
                56.4562873840332,
                67.14566040039063,
                110.26828002929688
            ]
        },
        {
            "frame": 17,
            "rtt": [
                44.526371002197269,
                198.87730407714845,
                56.433189392089847,
                67.13175201416016,
                96.1041030883789
            ]
        },
        {
            "frame": 18,
            "rtt": [
                43.03958511352539,
                54.117431640625,
                60.97426223754883,
                67.12581634521485,
                78.25309753417969
            ]
        },
        {
            "frame": 19,
            "rtt": [
                50.442420959472659,
                59.37123107910156,
                74.29238891601563
            ]
        },
        {
            "frame": 20,
            "rtt": [
                38.10779571533203,
                45.41436767578125,
                42.68998336791992,
                58.24849319458008
            ]
        },
        {
            "frame": 21,
            "rtt": [
                68.0764389038086,
                57.605255126953128,
                53.95258331298828,
                59.36225891113281,
                74.08831024169922
            ]
        },
        {
            "frame": 22,
            "rtt": [
                90.09315490722656,
                50.45476150512695,
                59.366519927978519,
                73.9822998046875
            ]
        },
        {
            "frame": 23,
            "rtt": [
                37.80742645263672,
                40.4375114440918,
                45.57365798950195,
                38.29042434692383,
                58.50376892089844
            ]
        },
        {
            "frame": 24,
            "rtt": [
                37.86087417602539,
                40.495201110839847,
                45.633827209472659,
                38.36216354370117,
                58.597869873046878
            ]
        },
        {
            "frame": 25,
            "rtt": [
                61.12409973144531,
                63.19011688232422,
                89.7310791015625,
                69.02168273925781
            ]
        },
        {
            "frame": 26,
            "rtt": [
                55.167503356933597,
                176.41786193847657,
                89.62104034423828,
                109.6382827758789
            ]
        },
        {
            "frame": 27,
            "rtt": [
                48.142417907714847,
                53.97011947631836,
                60.13531494140625,
                68.99638366699219
            ]
        },
        {
            "frame": 28,
            "rtt": [
                28.682390213012697,
                35.880977630615237,
                176.73678588867188,
                73.51504516601563
            ]
        },
        {
            "frame": 29,
            "rtt": [
                59.38304901123047,
                80.16844940185547,
                89.33522033691406,
                59.84061813354492
            ]
        },
        {
            "frame": 30,
            "rtt": [
                42.4739990234375,
                54.606414794921878,
                61.778804779052737,
                89.91559600830078,
                106.20001220703125
            ]
        },
        {
            "frame": 31,
            "rtt": [
                42.5931396484375,
                54.48841857910156,
                61.92598342895508,
                89.94692993164063,
                106.29515075683594
            ]
        },
        {
            "frame": 32,
            "rtt": [
                27.77631378173828,
                80.79002380371094,
                54.08209991455078,
                69.09657287597656
            ]
        },
        {
            "frame": 33,
            "rtt": [
                44.836212158203128,
                54.280887603759769,
                79.13886260986328
            ]
        },
        {
            "frame": 34,
            "rtt": [
                44.69059753417969,
                55.529205322265628,
                73.22166442871094
            ]
        },
        {
            "frame": 35,
            "rtt": [
                57.35122299194336,
                43.9764404296875,
                47.058921813964847,
                58.60285186767578
            ]
        },
        {
            "frame": 36,
            "rtt": [
                53.634883880615237,
                32.517574310302737,
                43.94850540161133,
                47.142887115478519,
                110.7205581665039
            ]
        },
        {
            "frame": 37,
            "rtt": [
                76.2940444946289,
                74.33187103271485,
                196.0789794921875
            ]
        },
        {
            "frame": 38,
            "rtt": [
                55.795352935791019,
                59.59135818481445,
                63.91061019897461
            ]
        },
        {
            "frame": 39,
            "rtt": [
                53.39010238647461,
                59.54243850708008,
                75.46174621582031
            ]
        },
        {
            "frame": 40,
            "rtt": [
                34.32271194458008,
                47.15277862548828,
                53.408905029296878,
                84.76370239257813,
                105.41189575195313
            ]
        },
        {
            "frame": 41,
            "rtt": [
                34.145111083984378,
                47.203453063964847,
                53.433433532714847,
                59.46223068237305,
                87.89651489257813
            ]
        },
        {
            "frame": 42,
            "rtt": [
                34.70551681518555,
                47.46879959106445,
                74.83748626708985,
                84.82404327392578,
                93.11917877197266
            ]
        },
        {
            "frame": 43,
            "rtt": [
                31.531312942504884,
                38.62546920776367,
                50.82020950317383,
                42.40126419067383,
                58.03060531616211
            ]
        },
        {
            "frame": 44,
            "rtt": [
                50.85356903076172,
                48.041717529296878,
                64.13961791992188
            ]
        },
        {
            "frame": 45,
            "rtt": [
                55.35786056518555,
                60.852230072021487,
                53.32001495361328,
                86.83096313476563,
                96.12957000732422
            ]
        },
        {
            "frame": 46,
            "rtt": [
                100.80651092529297,
                54.040382385253909,
                59.364227294921878,
                96.1633529663086
            ]
        },
        {
            "frame": 47,
            "rtt": [
                38.15828323364258,
                45.45954513549805,
                42.78651428222656,
                58.32197952270508
            ]
        },
        {
            "frame": 48,
            "rtt": [
                75.0056381225586,
                79.58594512939453,
                71.93818664550781,
                67.17764282226563,
                79.55902862548828
            ]
        },
        {
            "frame": 49,
            "rtt": [
                42.826805114746097,
                50.173484802246097,
                53.81348419189453,
                50.46871566772461,
                93.83026123046875
            ]
        },
        {
            "frame": 50,
            "rtt": [
                61.00139617919922,
                75.20682525634766,
                74.12664031982422,
                38.35577392578125,
                58.58958053588867
            ]
        }
    ]
}