{
    "latencies": [
        {
            "frame": 0,
            "rtt": []
        },
        {
            "frame": 1,
            "rtt": [
                28.680429458618165,
                35.88442611694336,
                39.33100128173828,
                53.53548049926758,
                68.99706268310547
            ]
        },
        {
            "frame": 2,
            "rtt": [
                32.557960510253909,
                44.07914352416992,
                46.954994201660159,
                46.69342041015625,
                59.84275436401367
            ]
        },
        {
            "frame": 3,
            "rtt": [
                28.60602569580078,
                36.02240753173828,
                39.24047088623047,
                53.4945068359375,
                69.00772094726563
            ]
        },
        {
            "frame": 4,
            "rtt": [
                27.887649536132814,
                34.47900390625,
                38.91307067871094,
                46.742252349853519,
                59.931007385253909
            ]
        },
        {
            "frame": 5,
            "rtt": [
                27.826793670654298,
                36.29648208618164,
                39.09764862060547,
                54.09574508666992,
                69.06260681152344
            ]
        },
        {
            "frame": 6,
            "rtt": [
                27.771791458129884,
                34.45769500732422,
                38.99918746948242,
                47.76739501953125,
                60.12173843383789
            ]
        },
        {
            "frame": 7,
            "rtt": [
                27.722593307495118,
                32.68598175048828,
                44.04932403564453,
                46.916343688964847,
                57.591007232666019
            ]
        },
        {
            "frame": 8,
            "rtt": [
                28.361692428588868,
                36.73990249633789,
                58.93882751464844,
                53.37778854370117,
                63.970767974853519
            ]
        },
        {
            "frame": 9,
            "rtt": [
                31.552499771118165,
                39.08161544799805,
                59.12303924560547,
                53.36984634399414,
                64.06745147705078
            ]
        },
        {
            "frame": 10,
            "rtt": [
                31.516748428344728,
                46.606285095214847,
                61.71297073364258,
                55.64752960205078,
                75.74263763427735
            ]
        },
        {
            "frame": 11,
            "rtt": [
                27.58390998840332,
                32.46556854248047,
                48.94690704345703,
                47.24149703979492,
                57.71909713745117
            ]
        },
        {
            "frame": 12,
            "rtt": [
                31.474227905273439,
                38.83714294433594,
                53.3779182434082,
                59.58688735961914,
                75.54241180419922
            ]
        },
        {
            "frame": 13,
            "rtt": [
                31.467378616333009,
                38.77460861206055,
                50.79230880737305,
                44.63593673706055,
                63.91889572143555
            ]
        },
        {
            "frame": 14,
            "rtt": [
                27.54087257385254,
                32.35192108154297,
                45.187442779541019,
                42.18281555175781,
                57.858665466308597
            ]
        },
        {
            "frame": 15,
            "rtt": [
                31.482196807861329,
                38.679107666015628,
                50.787269592285159,
                44.65129089355469,
                74.74633026123047
            ]
        },
        {
            "frame": 16,
            "rtt": [
                27.541305541992189,
                32.30038833618164,
                45.24973678588867,
                42.32706069946289,
                57.97282791137695
            ]
        },
        {
            "frame": 17,
            "rtt": [
                31.534324645996095,
                38.62398147583008,
                45.2858772277832,
                42.4085693359375,
                58.03627395629883
            ]
        },
        {
            "frame": 18,
            "rtt": [
                33.55091857910156,
                47.246360778808597,
                54.21089553833008,
                59.384464263916019,
                58.10397720336914
            ]
        },
        {
            "frame": 19,
            "rtt": [
                45.79520797729492,
                50.902103424072269,
                45.185752868652347,
                59.37123107910156,
                74.29238891601563
            ]
        },
        {
            "frame": 20,
            "rtt": [
                50.26212692260742,
                38.10779571533203,
                45.41436767578125,
                42.68998336791992,
                58.24849319458008
            ]
        },
        {
            "frame": 21,
            "rtt": [
                40.33360290527344,
                38.16326904296875,
                45.4639778137207,
                42.79591751098633,
                58.32912826538086
            ]
        },
        {
            "frame": 22,
            "rtt": [
                40.38368225097656,
                45.52116012573242,
                38.22414016723633,
                40.175079345703128,
                58.418296813964847
            ]
        },
        {
            "frame": 23,
            "rtt": [
                37.80742645263672,
                40.4375114440918,
                45.57365798950195,
                38.29042434692383,
                58.50376892089844
            ]
        },
        {
            "frame": 24,
            "rtt": [
                39.750465393066409,
                46.2729377746582,
                51.28231430053711,
                45.28971481323242,
                58.597869873046878
            ]
        },
        {
            "frame": 25,
            "rtt": [
                39.6391487121582,
                45.34001159667969,
                50.12763977050781,
                53.68378448486328,
                73.72723388671875
            ]
        },
        {
            "frame": 26,
            "rtt": [
                34.625125885009769,
                38.8112907409668,
                38.52237319946289,
                46.59941482543945,
                59.6342658996582
            ]
        },
        {
            "frame": 27,
            "rtt": [
                34.576873779296878,
                38.82703399658203,
                38.61088562011719,
                46.62348556518555,
                59.69532775878906
            ]
        },
        {
            "frame": 28,
            "rtt": [
                32.428192138671878,
                42.94126892089844,
                39.333343505859378,
                53.53651809692383,
                68.99693298339844
            ]
        },
        {
            "frame": 29,
            "rtt": [
                28.611804962158204,
                36.01091384887695,
                39.24757766723633,
                55.43107223510742,
                73.45389556884766
            ]
        },
        {
            "frame": 30,
            "rtt": [
                28.548124313354493,
                36.14534378051758,
                39.176849365234378,
                53.45506286621094,
                59.92341613769531
            ]
        },
        {
            "frame": 31,
            "rtt": [
                32.82645797729492,
                44.06855392456055,
                38.949485778808597,
                47.68534851074219,
                60.014495849609378
            ]
        },
        {
            "frame": 32,
            "rtt": [
                27.77631378173828,
                34.457881927490237,
                38.99494552612305,
                47.76057434082031,
                60.11286544799805
            ]
        },
        {
            "frame": 33,
            "rtt": [
                27.726619720458986,
                32.69160842895508,
                44.05318832397461,
                46.910430908203128,
                73.26549530029297
            ]
        },
        {
            "frame": 34,
            "rtt": [
                27.682743072509767,
                32.628604888916019,
                44.011356353759769,
                46.981414794921878,
                57.61552810668945
            ]
        },
        {
            "frame": 35,
            "rtt": [
                31.556049346923829,
                46.47288131713867,
                61.83885192871094,
                55.58024978637695,
                73.89356231689453
            ]
        },
        {
            "frame": 36,
            "rtt": [
                31.519472122192384,
                38.998291015625,
                43.94850540161133,
                47.142887115478519,
                57.677955627441409
            ]
        },
        {
            "frame": 37,
            "rtt": [
                27.585948944091798,
                32.4694938659668,
                48.944801330566409,
                47.23332977294922,
                57.71561050415039
            ]
        },
        {
            "frame": 38,
            "rtt": [
                33.956302642822269,
                46.860958099365237,
                55.795352935791019,
                59.59135818481445,
                57.754783630371097
            ]
        },
        {
            "frame": 39,
            "rtt": [
                31.467599868774415,
                38.779544830322269,
                50.79346466064453,
                44.63578414916992,
                75.46174621582031
            ]
        },
        {
            "frame": 40,
            "rtt": [
                27.5413875579834,
                32.35457229614258,
                50.78486633300781,
                44.6398811340332,
                63.939937591552737
            ]
        },
        {
            "frame": 41,
            "rtt": [
                34.145111083984378,
                47.203453063964847,
                53.433433532714847,
                59.46223068237305,
                63.97367858886719
            ]
        },
        {
            "frame": 42,
            "rtt": [
                33.94654083251953,
                47.21076965332031,
                52.531673431396487,
                42.32029724121094,
                57.96753692626953
            ]
        },
        {
            "frame": 43,
            "rtt": [
                27.549335479736329,
                32.283287048339847,
                45.28260803222656,
                42.40126419067383,
                58.03060531616211
            ]
        },
        {
            "frame": 44,
            "rtt": [
                33.566795349121097,
                47.24433135986328,
                45.3217887878418,
                42.48841857910156,
                58.097957611083987
            ]
        },
        {
            "frame": 45,
            "rtt": [
                45.78932189941406,
                50.897789001464847,
                45.186187744140628,
                47.98701095581055,
                64.21780395507813
            ]
        },
        {
            "frame": 46,
            "rtt": [
                50.26522445678711,
                50.44072723388672,
                45.41022872924805,
                42.681095123291019,
                58.241729736328128
            ]
        },
        {
            "frame": 47,
            "rtt": [
                40.329444885253909,
                38.15828323364258,
                45.45954513549805,
                42.78651428222656,
                58.32197952270508
            ]
        },
        {
            "frame": 48,
            "rtt": [
                40.37917709350586,
                45.51639175415039,
                38.21866989135742,
                40.172767639160159,
                58.41073989868164
            ]
        },
        {
            "frame": 49,
            "rtt": [
                37.80294418334961,
                40.432682037353519,
                45.568607330322269,
                50.46871566772461,
                73.91095733642578
            ]
        },
        {
            "frame": 50,
            "rtt": [
                37.85614013671875,
                40.490055084228519,
                45.62849044799805,
                38.35577392578125,
                58.58958053588867
            ]
        }
    ]
}