{
    "latencies": [
        {
            "frame": 0,
            "rtt": []
        },
        {
            "frame": 1,
            "rtt": [
                14.805558204650879,
                19.896730422973634,
                33.029541015625,
                80.9618911743164,
                81.55301666259766
            ]
        },
        {
            "frame": 2,
            "rtt": [
                23.490886688232423,
                65.90609741210938,
                98.7939453125,
                115.66316223144531,
                87.06878662109375
            ]
        },
        {
            "frame": 3,
            "rtt": [
                23.48920249938965,
                65.89215850830078,
                98.7779769897461,
                90.28207397460938,
                90.71280670166016
            ]
        },
        {
            "frame": 4,
            "rtt": [
                14.824800491333008,
                19.905025482177736,
                32.906551361083987,
                81.02186584472656,
                81.61383056640625
            ]
        },
        {
            "frame": 5,
            "rtt": [
                34.75506591796875,
                19.918699264526368,
                32.859275817871097,
                81.05951690673828,
                81.65162658691406
            ]
        },
        {
            "frame": 6,
            "rtt": [
                56.52103042602539,
                47.08242416381836,
                91.46366119384766,
                91.9137954711914
            ]
        },
        {
            "frame": 7,
            "rtt": [
                22.444765090942384,
                30.428346633911134,
                34.205780029296878,
                87.5560073852539,
                86.96400451660156
            ]
        },
        {
            "frame": 8,
            "rtt": [
                30.778671264648439,
                82.43720245361328,
                108.76264190673828,
                87.01824188232422
            ]
        },
        {
            "frame": 9,
            "rtt": [
                22.511524200439454,
                27.72736930847168,
                31.01072120666504,
                87.07746124267578,
                107.4007339477539
            ]
        },
        {
            "frame": 10,
            "rtt": [
                56.7768669128418,
                42.63218688964844,
                44.67242431640625,
                91.88400268554688,
                91.09903717041016
            ]
        },
        {
            "frame": 11,
            "rtt": [
                22.596641540527345,
                27.698566436767579,
                30.861013412475587,
                87.21102905273438,
                91.04442596435547
            ]
        },
        {
            "frame": 12,
            "rtt": [
                31.335142135620118,
                78.6440658569336,
                80.36608123779297,
                106.52719116210938,
                107.51236724853516
            ]
        },
        {
            "frame": 13,
            "rtt": [
                25.994985580444337,
                47.8315544128418,
                64.95866394042969,
                109.62670135498047,
                100.62130737304688
            ]
        },
        {
            "frame": 14,
            "rtt": [
                58.64714050292969,
                79.04595947265625,
                44.95035934448242,
                94.60585021972656,
                94.92585754394531
            ]
        },
        {
            "frame": 15,
            "rtt": [
                25.988054275512697,
                43.20733642578125,
                45.04191970825195,
                94.49076080322266,
                97.17411804199219
            ]
        },
        {
            "frame": 16,
            "rtt": [
                25.722074508666993,
                65.70630645751953,
                65.69589233398438,
                131.01882934570313
            ]
        },
        {
            "frame": 17,
            "rtt": [
                19.160573959350587,
                29.526283264160158,
                30.533071517944337,
                86.74644470214844,
                87.31307220458985
            ]
        },
        {
            "frame": 18,
            "rtt": [
                20.82302474975586,
                29.471948623657228,
                30.49591064453125,
                86.72325897216797,
                87.29412841796875
            ]
        },
        {
            "frame": 19,
            "rtt": [
                123.06663513183594,
                47.2888298034668,
                48.12836456298828,
                95.88607025146485,
                96.15955352783203
            ]
        },
        {
            "frame": 20,
            "rtt": [
                18.086130142211915,
                29.85239028930664,
                30.69540023803711,
                89.85948944091797,
                103.582763671875
            ]
        },
        {
            "frame": 21,
            "rtt": [
                23.064380645751954,
                29.81345558166504,
                30.6595458984375,
                90.02847290039063,
                100.37129974365235
            ]
        },
        {
            "frame": 22,
            "rtt": [
                44.38079833984375,
                52.489566802978519,
                30.629974365234376,
                90.21111297607422,
                90.38771057128906
            ]
        },
        {
            "frame": 23,
            "rtt": [
                18.58002281188965,
                29.755826950073243,
                30.606678009033204,
                90.40744018554688,
                81.49497985839844
            ]
        },
        {
            "frame": 24,
            "rtt": [
                17.14981460571289,
                21.338125228881837,
                22.044601440429689,
                91.67378997802735,
                92.35298919677735
            ]
        },
        {
            "frame": 25,
            "rtt": [
                44.629207611083987,
                54.44673538208008,
                51.490562438964847,
                102.8001480102539,
                81.50325012207031
            ]
        },
        {
            "frame": 26,
            "rtt": [
                33.273075103759769,
                43.82736587524414,
                22.207481384277345,
                87.9419174194336,
                87.39360809326172
            ]
        },
        {
            "frame": 27,
            "rtt": [
                47.4563102722168,
                21.55907440185547,
                22.296161651611329,
                87.80908203125,
                87.2765121459961
            ]
        },
        {
            "frame": 28,
            "rtt": [
                22.918302536010743,
                40.112396240234378,
                55.33159255981445,
                91.32841491699219,
                91.30513000488281
            ]
        },
        {
            "frame": 29,
            "rtt": [
                20.962295532226564,
                43.62950897216797,
                70.73146057128906,
                100.92642974853516,
                99.51657104492188
            ]
        },
        {
            "frame": 30,
            "rtt": [
                16.846113204956056,
                21.82872200012207,
                55.47163772583008,
                93.35045623779297,
                93.58070373535156
            ]
        },
        {
            "frame": 31,
            "rtt": [
                20.151573181152345,
                28.941946029663087,
                71.21404266357422,
                103.34833526611328,
                93.92985534667969
            ]
        },
        {
            "frame": 32,
            "rtt": [
                29.078977584838868,
                60.9344367980957,
                63.79092788696289
            ]
        },
        {
            "frame": 33,
            "rtt": [
                30.64546775817871,
                97.21794128417969,
                96.73252868652344
            ]
        },
        {
            "frame": 34,
            "rtt": [
                25.540897369384767,
                46.67683792114258,
                47.33177947998047,
                102.36181640625,
                103.1309814453125
            ]
        },
        {
            "frame": 35,
            "rtt": [
                25.59607696533203,
                42.52747344970703,
                43.32207489013672,
                91.88005065917969,
                95.29212951660156
            ]
        },
        {
            "frame": 36,
            "rtt": [
                22.54812240600586,
                48.197120666503909,
                51.07665252685547,
                99.64623260498047,
                96.37194061279297
            ]
        },
        {
            "frame": 37,
            "rtt": [
                26.04267692565918,
                46.288246154785159,
                48.874305725097659,
                106.82832336425781,
                106.5366439819336
            ]
        },
        {
            "frame": 38,
            "rtt": [
                26.01466941833496,
                46.29912185668945,
                64.70340728759766,
                106.49659729003906,
                102.40682220458985
            ]
        },
        {
            "frame": 39,
            "rtt": [
                25.996109008789064,
                66.2231674194336,
                66.54489135742188,
                101.61563873291016,
                102.44522094726563
            ]
        },
        {
            "frame": 40,
            "rtt": [
                47.734527587890628,
                48.551849365234378,
                97.05416107177735,
                97.09945678710938
            ]
        },
        {
            "frame": 41,
            "rtt": [
                36.61931610107422,
                82.10691833496094,
                82.00160217285156,
                97.2435531616211,
                98.71823120117188
            ]
        },
        {
            "frame": 42,
            "rtt": [
                31.768051147460939,
                95.55484771728516,
                95.74910736083985
            ]
        },
        {
            "frame": 43,
            "rtt": [
                31.82740020751953,
                65.92210388183594,
                65.92896270751953,
                131.29937744140626
            ]
        },
        {
            "frame": 44,
            "rtt": [
                31.896347045898439,
                87.38827514648438,
                87.09125518798828,
                135.5771026611328,
                117.14372253417969
            ]
        },
        {
            "frame": 45,
            "rtt": [
                38.947025299072269,
                44.84418487548828,
                45.482357025146487,
                92.8245849609375,
                92.1729507446289
            ]
        },
        {
            "frame": 46,
            "rtt": [
                14.984878540039063,
                20.11009979248047,
                21.164213180541993,
                80.9419174194336,
                81.51950073242188
            ]
        },
        {
            "frame": 47,
            "rtt": [
                18.22992706298828,
                29.81655502319336,
                30.662399291992189,
                80.92617797851563,
                81.50662994384766
            ]
        },
        {
            "frame": 48,
            "rtt": [
                14.9032564163208,
                20.02202606201172,
                21.104053497314454,
                80.91556549072266,
                81.49846649169922
            ]
        },
        {
            "frame": 49,
            "rtt": [
                44.45042419433594,
                51.48839569091797,
                52.079063415527347,
                80.91004943847656,
                81.49504852294922
            ]
        },
        {
            "frame": 50,
            "rtt": [
                14.84613037109375,
                19.956972122192384,
                21.063488006591798,
                80.90961456298828,
                92.00978088378906
            ]
        }
    ]
}