{
    "latencies": [
        {
            "frame": 0,
            "rtt": []
        },
        {
            "frame": 1,
            "rtt": [
                106.08609771728516,
                113.01715087890625,
                110.6942367553711,
                111.6072006225586,
                114.77593231201172
            ]
        },
        {
            "frame": 2,
            "rtt": [
                106.10880279541016,
                111.41592407226563,
                113.11141967773438,
                116.53500366210938,
                111.84833526611328
            ]
        },
        {
            "frame": 3,
            "rtt": [
                104.85337829589844,
                110.70719146728516,
                113.11743927001953,
                116.53813171386719,
                115.32283782958985
            ]
        },
        {
            "frame": 4,
            "rtt": [
                100.47563171386719,
                106.89781951904297,
                108.91378021240235,
                111.1109619140625,
                110.26026153564453
            ]
        },
        {
            "frame": 5,
            "rtt": [
                106.18106842041016,
                111.4197769165039,
                108.94063568115235,
                111.11034393310547,
                110.3080825805664
            ]
        },
        {
            "frame": 6,
            "rtt": [
                104.56446838378906,
                110.78848266601563,
                110.05620574951172,
                114.6033935546875,
                111.62818145751953
            ]
        },
        {
            "frame": 7,
            "rtt": [
                100.49066925048828,
                105.70947265625,
                110.31034088134766,
                107.48599243164063,
                111.12370300292969
            ]
        },
        {
            "frame": 8,
            "rtt": [
                106.3475570678711,
                112.96910858154297,
                110.87904357910156,
                111.87957763671875,
                115.73969268798828
            ]
        },
        {
            "frame": 9,
            "rtt": [
                106.4189682006836,
                112.98249053955078,
                110.9351577758789,
                111.83600616455078,
                115.68865203857422
            ]
        },
        {
            "frame": 10,
            "rtt": [
                27.144989013671876,
                35.7360725402832,
                110.99847412109375,
                108.51236724853516,
                113.01124572753906
            ]
        },
        {
            "frame": 11,
            "rtt": [
                26.979389190673829,
                34.862728118896487,
                111.78305053710938,
                108.56417083740235,
                114.49932098388672
            ]
        },
        {
            "frame": 12,
            "rtt": [
                25.547849655151368,
                32.91485595703125,
                108.40047454833985,
                108.51959228515625,
                114.83599090576172
            ]
        },
        {
            "frame": 13,
            "rtt": [
                26.664369583129884,
                34.964881896972659,
                111.77592468261719,
                105.83686065673828,
                111.11695098876953
            ]
        },
        {
            "frame": 14,
            "rtt": [
                25.743408203125,
                33.00410842895508,
                108.30681610107422,
                105.87059783935547,
                111.11798095703125
            ]
        },
        {
            "frame": 15,
            "rtt": [
                25.85698127746582,
                33.16099548339844,
                107.52891540527344,
                107.54875946044922,
                111.37730407714844
            ]
        },
        {
            "frame": 16,
            "rtt": [
                24.26674461364746,
                32.24598693847656,
                105.65711975097656,
                111.9920883178711,
                115.64733123779297
            ]
        },
        {
            "frame": 17,
            "rtt": [
                26.107648849487306,
                33.304134368896487,
                107.45503997802735,
                112.0055923461914,
                115.68659210205078
            ]
        },
        {
            "frame": 18,
            "rtt": [
                25.254478454589845,
                33.388404846191409,
                109.78401184082031,
                107.1622085571289,
                113.15775299072266
            ]
        },
        {
            "frame": 19,
            "rtt": [
                26.505537033081056,
                34.2957649230957,
                32.639217376708987,
                105.68953704833985,
                107.67811584472656
            ]
        },
        {
            "frame": 20,
            "rtt": [
                25.077314376831056,
                34.425315856933597,
                33.68047332763672,
                109.4476318359375,
                109.64990997314453
            ]
        },
        {
            "frame": 21,
            "rtt": [
                26.897417068481447,
                34.564334869384769,
                32.574058532714847,
                105.62760925292969,
                105.91756439208985
            ]
        },
        {
            "frame": 22,
            "rtt": [
                24.72122573852539,
                33.72940444946289,
                32.550941467285159,
                105.57754516601563,
                105.8929214477539
            ]
        },
        {
            "frame": 23,
            "rtt": [
                24.74126625061035,
                32.534141540527347,
                33.291419982910159
            ]
        },
        {
            "frame": 24,
            "rtt": [
                109.01190185546875,
                111.22095489501953,
                111.4227523803711
            ]
        },
        {
            "frame": 25,
            "rtt": [
                105.30937957763672,
                114.98108673095703,
                115.44493865966797
            ]
        },
        {
            "frame": 26,
            "rtt": [
                100.51282501220703,
                111.1644058227539,
                111.50010681152344
            ]
        },
        {
            "frame": 27,
            "rtt": [
                106.07118225097656,
                116.44636535644531,
                115.4382553100586
            ]
        },
        {
            "frame": 28,
            "rtt": [
                106.08557891845703,
                113.0147933959961,
                111.43569946289063,
                115.452392578125,
                116.48567199707031
            ]
        },
        {
            "frame": 29,
            "rtt": [
                100.4788589477539,
                106.93184661865235,
                108.88882446289063,
                111.11711883544922,
                110.2158203125
            ]
        },
        {
            "frame": 30,
            "rtt": [
                104.75682067871094,
                110.72496032714844,
                110.02250671386719,
                116.58998107910156,
                115.2853012084961
            ]
        },
        {
            "frame": 31,
            "rtt": [
                100.4764633178711,
                106.87278747558594,
                108.93811798095703,
                111.11016082763672,
                110.30362701416016
            ]
        },
        {
            "frame": 32,
            "rtt": [
                106.22413635253906,
                111.44029235839844,
                108.96846771240235,
                111.11400604248047,
                110.35753631591797
            ]
        },
        {
            "frame": 33,
            "rtt": [
                104.49279022216797,
                108.83966827392578,
                111.4751968383789,
                113.12931060791016,
                116.80867004394531
            ]
        },
        {
            "frame": 34,
            "rtt": [
                100.5021743774414,
                108.77685546875,
                105.72051239013672,
                107.50540161132813,
                111.13629913330078
            ]
        },
        {
            "frame": 35,
            "rtt": [
                104.36314392089844,
                111.46660614013672,
                108.68611145019531,
                108.58080291748047,
                113.08214569091797
            ]
        },
        {
            "frame": 36,
            "rtt": [
                25.390188217163087,
                32.57223129272461,
                105.75525665283203,
                107.56259155273438,
                111.17837524414063
            ]
        },
        {
            "frame": 37,
            "rtt": [
                24.399309158325197,
                32.885833740234378,
                108.45903015136719,
                108.56841278076172,
                114.49433135986328
            ]
        },
        {
            "frame": 38,
            "rtt": [
                26.832685470581056,
                35.144447326660159,
                111.77406311035156,
                105.8042221069336,
                111.12342834472656
            ]
        },
        {
            "frame": 39,
            "rtt": [
                26.677474975585939,
                32.456424713134769,
                107.68648529052735,
                105.8340835571289,
                111.11714935302735
            ]
        },
        {
            "frame": 40,
            "rtt": [
                26.52813720703125,
                34.817588806152347,
                111.78790283203125,
                105.86753845214844,
                111.11760711669922
            ]
        },
        {
            "frame": 41,
            "rtt": [
                26.384981155395509,
                32.287418365478519,
                105.65673828125,
                107.54714965820313,
                111.37276458740235
            ]
        },
        {
            "frame": 42,
            "rtt": [
                24.26752471923828,
                32.24903106689453,
                107.49152374267578,
                109.95216369628906,
                112.71734619140625
            ]
        },
        {
            "frame": 43,
            "rtt": [
                24.261747360229493,
                32.21664810180664,
                105.66210174560547,
                107.59709167480469,
                111.48782348632813
            ]
        },
        {
            "frame": 44,
            "rtt": [
                25.26290512084961,
                33.37672424316406,
                107.63223266601563,
                106.03820037841797,
                111.55364990234375
            ]
        },
        {
            "frame": 45,
            "rtt": [
                25.169082641601564,
                34.285003662109378,
                33.36909103393555,
                107.16275024414063,
                107.6741714477539
            ]
        },
        {
            "frame": 46,
            "rtt": [
                25.084209442138673,
                34.17967987060547,
                33.25983428955078,
                106.0549087524414,
                105.94862365722656
            ]
        },
        {
            "frame": 47,
            "rtt": [
                24.70751953125,
                33.79075241088867,
                32.576358795166019,
                105.63207244873047,
                105.91986083984375
            ]
        },
        {
            "frame": 48,
            "rtt": [
                24.719818115234376,
                33.73406982421875,
                33.062496185302737,
                106.0822525024414,
                108.67176055908203
            ]
        },
        {
            "frame": 49,
            "rtt": [
                24.88673210144043,
                32.53533935546875,
                33.29392623901367
            ]
        },
        {
            "frame": 50,
            "rtt": [
                102.3546371459961,
                111.22389221191406,
                111.41988372802735
            ]
        }
    ]
}